setup.cfg
setup.py
Ansible_Toolkit.egg-info/PKG-INFO
Ansible_Toolkit.egg-info/SOURCES.txt
Ansible_Toolkit.egg-info/dependency_links.txt
Ansible_Toolkit.egg-info/requires.txt
Ansible_Toolkit.egg-info/top_level.txt
ansible_toolkit/__init__.py
ansible_toolkit/exceptions.py
ansible_toolkit/git_diff.py
ansible_toolkit/show_template.py
ansible_toolkit/show_vars.py
ansible_toolkit/utils.py
ansible_toolkit/utils_ansible.py
ansible_toolkit/vault.py
ansible_toolkit.egg-info/SOURCES.txt
bin/atk-git-diff
bin/atk-show-template
bin/atk-show-vars
bin/atk-vault