Metadata-Version: 1.0
Name: ansible-toolkit
Version: 1.3.1
Summary: The missing Ansible tools
Home-page: http://github.com/dellis23/ansible-toolkit
Author: Daniel Ellis
Author-email: ellisd23@gmail.com
License: GPLv3
Platform: UNKNOWN
